pointgroup/__init__.py
pointgroup/element_data.py
pointgroup/grid.py
pointgroup/operations.py
pointgroup/tools.py
pointgroup-0.4.4.dist-info/licenses/LICENSE
pointgroup-0.4.4.dist-info/METADATA
pointgroup-0.4.4.dist-info/WHEEL
pointgroup-0.4.4.dist-info/top_level.txt
pointgroup-0.4.4.dist-info/RECORD
