Metadata-Version: 2.4
Name: pointgroup
Version: 0.4.4
Summary: pointgroup module
Home-page: https://github.com/abelcarreras/pointgroup
Author: Abel Carreras
Author-email: abelcarreras83@gmail.com
License: MIT License
License-File: LICENSE
Requires-Dist: numpy
Dynamic: author
Dynamic: author-email
Dynamic: description
Dynamic: description-content-type
Dynamic: home-page
Dynamic: license
Dynamic: license-file
Dynamic: requires-dist
Dynamic: summary
